{"eDifficulty":0,"carDatas":[{"eColor":5,"direction":7,"size":1,"position":{"x":-4.23,"y":-0.170000017}},{"eColor":6,"direction":7,"size":1,"position":{"x":-2.96,"y":-1.27}},{"eColor":2,"direction":7,"size":1,"position":{"x":-4.2,"y":-1.82999992}},{"eColor":7,"direction":7,"size":1,"position":{"x":-2.9,"y":-2.99}},{"eColor":0,"direction":7,"size":2,"position":{"x":-1.97,"y":-0.54}},{"eColor":1,"direction":7,"size":2,"position":{"x":-1.33458638,"y":-2.752363}},{"eColor":4,"direction":7,"size":0,"position":{"x":-1.61000013,"y":-3.98}},{"eColor":2,"direction":7,"size":0,"position":{"x":-0.76,"y":0.0}},{"eColor":5,"direction":7,"size":1,"position":{"x":0.480000019,"y":-1.10000014}},{"eColor":7,"direction":7,"size":1,"position":{"x":1.13000011,"y":-0.199999988}},{"eColor":2,"direction":7,"size":0,"position":{"x":-0.370000124,"y":-1.82999992}},{"eColor":6,"direction":1,"size":2,"position":{"x":1.07458627,"y":-2.497637}},{"eColor":0,"direction":1,"size":0,"position":{"x":2.57000017,"y":-1.06999993}},{"eColor":2,"direction":3,"size":0,"position":{"x":3.23999977,"y":-0.0600000024}},{"eColor":5,"direction":1,"size":1,"position":{"x":4.14,"y":-1.3499999}},{"eColor":4,"direction":1,"size":1,"position":{"x":2.89999962,"y":-2.44999981}},{"eColor":2,"direction":1,"size":2,"position":{"x":1.32171345,"y":-3.81601357}},{"eColor":3,"direction":1,"size":0,"position":{"x":3.88999987,"y":-3.07000017}},{"eColor":7,"direction":1,"size":0,"position":{"x":2.79,"y":-4.09}},{"eColor":0,"direction":1,"size":0,"position":{"x":1.69,"y":-5.13}},{"eColor":3,"direction":3,"size":2,"position":{"x":-4.14,"y":-3.63}},{"eColor":2,"direction":3,"size":1,"position":{"x":-2.37,"y":-5.04}},{"eColor":5,"direction":7,"size":1,"position":{"x":-4.11,"y":-5.13}},{"eColor":6,"direction":1,"size":2,"position":{"x":3.81,"y":-4.93000031}}],"guestDatas":[{"eColor":5,"number":3},{"eColor":6,"number":3},{"eColor":5,"number":3},{"eColor":1,"number":5},{"eColor":2,"number":4},{"eColor":7,"number":4},{"eColor":5,"number":3},{"eColor":6,"number":3},{"eColor":7,"number":2},{"eColor":2,"number":2},{"eColor":0,"number":8},{"eColor":2,"number":2},{"eColor":4,"number":4},{"eColor":5,"number":3},{"eColor":1,"number":3},{"eColor":2,"number":6},{"eColor":0,"number":4},{"eColor":4,"number":2},{"eColor":1,"number":2},{"eColor":2,"number":4},{"eColor":6,"number":6},{"eColor":2,"number":4},{"eColor":3,"number":2},{"eColor":2,"number":4},{"eColor":0,"number":2},{"eColor":5,"number":3},{"eColor":6,"number":4},{"eColor":7,"number":2},{"eColor":2,"number":2},{"eColor":0,"number":4},{"eColor":7,"number":4},{"eColor":4,"number":4},{"eColor":3,"number":2},{"eColor":2,"number":4},{"eColor":3,"number":6},{"eColor":5,"number":3},{"eColor":2,"number":2},{"eColor":6,"number":4},{"eColor":3,"number":8},{"eColor":7,"number":2},{"eColor":6,"number":2},{"eColor":7,"number":2},{"eColor":3,"number":4},{"eColor":0,"number":2},{"eColor":4,"number":2},{"eColor":6,"number":2},{"eColor":4,"number":6},{"eColor":0,"number":2},{"eColor":2,"number":2},{"eColor":0,"number":2},{"eColor":5,"number":3},{"eColor":2,"number":2},{"eColor":0,"number":2},{"eColor":6,"number":2},{"eColor":5,"number":3}],"garageDatas":[{"position":{"x":-0.25,"y":-5.02},"direction":1,"cars":[{"eColor":3,"direction":1,"size":0,"position":{"x":0.0,"y":0.0}},{"eColor":4,"direction":1,"size":0,"position":{"x":0.0,"y":0.0}},{"eColor":0,"direction":1,"size":0,"position":{"x":0.0,"y":0.0}},{"eColor":3,"direction":1,"size":0,"position":{"x":0.0,"y":0.0}},{"eColor":4,"direction":1,"size":0,"position":{"x":0.0,"y":0.0}},{"eColor":0,"direction":1,"size":0,"position":{"x":0.0,"y":0.0}},{"eColor":2,"direction":1,"size":0,"position":{"x":0.0,"y":0.0}}]}]}